zodiax/__init__.py
zodiax/base.py
zodiax/bayes.py
zodiax/equinox.py
zodiax/eqx.py
zodiax/filter.py
zodiax/jit.py
zodiax/optimisation.py
zodiax/tree.py
zodiax/trees.py
zodiax/dev/__init__.py
zodiax/dev/serialisation.py
zodiax/experimental/__init__.py
zodiax/experimental/jit.py
zodiax/experimental/serialisation.py
zodiax/test/__init__.py
zodiax-0.4.1.dist-info/.ipynb_checkpoints/SOURCES-checkpoint.txt
zodiax-0.4.1.dist-info/.ipynb_checkpoints/requires-checkpoint.txt
zodiax-0.4.1.dist-info/LICENSE
zodiax-0.4.1.dist-info/METADATA
zodiax-0.4.1.dist-info/WHEEL
zodiax-0.4.1.dist-info/top_level.txt
zodiax-0.4.1.dist-info/RECORD
