Metadata-Version: 2.1
Name: zodiax
Version: 0.4.1
Summary: Equinox extension for scientific programming
Home-page: https://github.com/LouisDesdoigts/zodiax
Author: Louis Desdoigts
Author-email: Louis.Desdoigts@sydney.edu.au
Project-URL: Bug Tracker, https://github.com/LouisDesdoigts/zodiax/issues
Classifier: Programming Language :: Python :: 3
Classifier: Operating System :: OS Independent
Requires-Python: >=3.8, <4
License-File: LICENSE
Requires-Dist: equinox
Requires-Dist: jax
Requires-Dist: jaxlib
Requires-Dist: jaxtyping
Requires-Dist: numpy
Requires-Dist: optax
Provides-Extra: docs
Requires-Dist: optax ; extra == 'docs'
Requires-Dist: matplotlib ; extra == 'docs'
Requires-Dist: jupyter ; extra == 'docs'
Requires-Dist: jupyterlab ; extra == 'docs'
Requires-Dist: tqdm ; extra == 'docs'
Requires-Dist: chainconsumer ; extra == 'docs'
Requires-Dist: numpyro ; extra == 'docs'
Requires-Dist: mkdocs ; extra == 'docs'
Requires-Dist: mkdocs-jupyter ; extra == 'docs'
Requires-Dist: mkdocs-same-dir ; extra == 'docs'
Requires-Dist: mkdocs-autorefs ; extra == 'docs'
Requires-Dist: mkdocs-simple-plugin ; extra == 'docs'
Requires-Dist: mkdocstrings-python ; extra == 'docs'
Requires-Dist: jupyter-contrib-nbextensions ; extra == 'docs'
Provides-Extra: tests
Requires-Dist: pytest ; extra == 'tests'
